neuroner/__init__.py
neuroner/__main__.py
neuroner/brat_to_conll.py
neuroner/conll_to_brat.py
neuroner/conlleval
neuroner/dataset.py
neuroner/entity_lstm.py
neuroner/evaluate.py
neuroner/neuromodel.py
neuroner/prepare_pretrained_model.py
neuroner/train.py
neuroner/utils.py
neuroner/utils_nlp.py
neuroner/utils_plots.py
neuroner/utils_tf.py
neuroner/data/conll2003/en/metadata
neuroner/data/conll2003/en/test.txt
neuroner/data/conll2003/en/train.txt
neuroner/data/conll2003/en/valid.txt
neuroner/data/example_unannotated_texts/deploy/news.txt
neuroner/data/example_unannotated_texts/deploy/some_random_text.txt
neuroner/data/i2b2_2014_deid/readme.md
neuroner/data/i2b2_2014_deid/xml_to_brat.py
neuroner/trained_models/performances.md
neuroner/trained_models/conll_2003_en/dataset.pickle
neuroner/trained_models/conll_2003_en/model.ckpt.data-00000-of-00001
neuroner/trained_models/conll_2003_en/model.ckpt.index
neuroner/trained_models/conll_2003_en/model.ckpt.meta
neuroner/trained_models/conll_2003_en/parameters.ini
neuroner/trained_models/i2b2_2014_glove_spacy_bioes/checkpoint
neuroner/trained_models/i2b2_2014_glove_spacy_bioes/dataset.pickle
neuroner/trained_models/i2b2_2014_glove_spacy_bioes/model.ckpt.data-00000-of-00001
neuroner/trained_models/i2b2_2014_glove_spacy_bioes/model.ckpt.index
neuroner/trained_models/i2b2_2014_glove_spacy_bioes/model.ckpt.meta
neuroner/trained_models/i2b2_2014_glove_spacy_bioes/parameters.ini
neuroner/trained_models/i2b2_2014_glove_stanford_bioes/checkpoint
neuroner/trained_models/i2b2_2014_glove_stanford_bioes/dataset.pickle
neuroner/trained_models/i2b2_2014_glove_stanford_bioes/model.ckpt.data-00000-of-00001
neuroner/trained_models/i2b2_2014_glove_stanford_bioes/model.ckpt.index
neuroner/trained_models/i2b2_2014_glove_stanford_bioes/model.ckpt.meta
neuroner/trained_models/i2b2_2014_glove_stanford_bioes/parameters.ini
neuroner/trained_models/mimic_glove_spacy_bioes/checkpoint
neuroner/trained_models/mimic_glove_spacy_bioes/dataset.pickle
pyneuroner-1.0.8.dist-info/LICENSE
pyneuroner-1.0.8.dist-info/METADATA
pyneuroner-1.0.8.dist-info/WHEEL
pyneuroner-1.0.8.dist-info/entry_points.txt
pyneuroner-1.0.8.dist-info/top_level.txt
pyneuroner-1.0.8.dist-info/RECORD
