Metadata-Version: 2.1
Name: pyneuroner
Version: 1.0.8
Summary: NeuroNER
Home-page: https://github.com/Franck-Dernoncourt/NeuroNER
License: UNKNOWN
Keywords: Named-entity recognition using neural networks
Platform: UNKNOWN
Requires-Dist: matplotlib (>=3.0.2)
Requires-Dist: networkx (>=2.2)
Requires-Dist: pycorenlp (>=0.3.0)
Requires-Dist: scikit-learn (>=0.20.2)
Requires-Dist: scipy (>=1.2.0)
Requires-Dist: spacy (>=2.0.18)
Provides-Extra: cpu
Requires-Dist: tensorflow (>=1.12.0) ; extra == 'cpu'
Provides-Extra: gpu
Requires-Dist: tensorflow-gpu (>=1.0.0) ; extra == 'gpu'
